<?xml version="1.0"?>
<scpd xmlns="urn:schemas-upnp-org:service-1-0">
	<specVersion>
		<major>1</major>
		<minor>0</minor>
	</specVersion>
	<serviceStateTable>
		<stateVariable>
			<name>MaxID</name>
			<dataType>ui4</dataType>
		</stateVariable>
		<stateVariable>
			<name>A_ARG_TYPE_UI4</name>
			<dataType>ui4</dataType>
		</stateVariable>
		<stateVariable>
			<name>A_ARG_TYPE_STRING</name>
			<dataType>string</dataType>
		</stateVariable>
		<stateVariable>
			<name>A_ARG_TYPE_BOOLEAN</name>
			<dataType>boolean</dataType>
			<defaultValue>0</defaultValue>
		</stateVariable>
	</serviceStateTable>
	<actionList>
		<action>
			<name>SendMessage</name>
			<argumentList>
				<argument>
					<name>type</name>
					<direction>in</direction>
					<relatedStateVariable>A_ARG_TYPE_STRING</relatedStateVariable>
				</argument>
				<argument>
					<name>data</name>
					<direction>in</direction>
					<relatedStateVariable>A_ARG_TYPE_STRING</relatedStateVariable>
				</argument>
			</argumentList>
		</action>
		<action>
			<name>Refresh</name>
			<argumentList>
			</argumentList>
		</action>
		<action>
			<name>CreateDevices</name>
			<argumentList>
				<argument>
					<name>items</name>
					<direction>in</direction>
					<relatedStateVariable>A_ARG_TYPE_STRING</relatedStateVariable>
				</argument>
			</argumentList>
		</action>
		<action>
			<name>Inclusion</name>
			<argumentList>
			</argumentList>
		</action>
		<action>
			<name>Associate</name>
			<argumentList>
				<argument>
					<name>address</name>
					<direction>in</direction>
					<relatedStateVariable>A_ARG_TYPE_STRING</relatedStateVariable>
				</argument>
				<argument>
					<name>endPoint</name>
					<direction>in</direction>
					<relatedStateVariable>A_ARG_TYPE_STRING</relatedStateVariable>
				</argument>
				<argument>
					<name>feature</name>
					<direction>in</direction>
					<relatedStateVariable>A_ARG_TYPE_STRING</relatedStateVariable>
				</argument>
				<argument>
					<name>association</name>
					<direction>in</direction>
					<relatedStateVariable>A_ARG_TYPE_STRING</relatedStateVariable>
				</argument>
			</argumentList>
		</action>
	</actionList>
</scpd>
